README.md
setup.py
trello_cli/__init__.py
trello_cli/commands.py
trello_cli/start.py
trello_cli.egg-info/PKG-INFO
trello_cli.egg-info/SOURCES.txt
trello_cli.egg-info/dependency_links.txt
trello_cli.egg-info/entry_points.txt
trello_cli.egg-info/requires.txt
trello_cli.egg-info/top_level.txt