Metadata-Version: 1.1
Name: trello-cli
Version: 0.1.1
Summary: Trello CLI
Home-page: https://github.com/whitef0x0/trello-cli
Author: David Baldwynn
Author-email: david@countable.ca
License: BSD License
Platform: UNKNOWN
Classifier: Programming Language :: Python :: 2.7
Classifier: License :: OSI Approved :: BSD License
